instabase/.DS_Store
instabase/__init__.py
instabase/apps/__init__.py
instabase/apps/__version__.py
instabase/apps/_utils.py
instabase/apps/client.py
instabase/apps/enums.py
instabase-0.0.3.dist-info/METADATA
instabase-0.0.3.dist-info/WHEEL
instabase-0.0.3.dist-info/entry_points.txt
instabase-0.0.3.dist-info/license_files/LICENSE
instabase-0.0.3.dist-info/RECORD
