Metadata-Version: 2.1
Name: instabase
Version: 0.0.3
Summary: SDK to access Instabase Apps
Project-URL: Bug Tracker, https://github.com/instabase/instabase-sdk-py/issues
Project-URL: Homepage, https://github.com/instabase/instabase-sdk-py
Author-email: Mohit Chawla <sdk@instabase.com>
License:                                  Apache License
Requires-Python: >=3.6
Requires-Dist: pytest
Requires-Dist: requests
Requires-Dist: validators
